sigopt/__init__.py
sigopt/compat.py
sigopt/endpoint.py
sigopt/exception.py
sigopt/interface.py
sigopt/objects.py
sigopt/requestor.py
sigopt/resource.py
sigopt/version.py
sigopt_python-1.1.1.dist-info/DESCRIPTION.rst
sigopt_python-1.1.1.dist-info/METADATA
sigopt_python-1.1.1.dist-info/RECORD
sigopt_python-1.1.1.dist-info/WHEEL
sigopt_python-1.1.1.dist-info/metadata.json
sigopt_python-1.1.1.dist-info/pbr.json
sigopt_python-1.1.1.dist-info/top_level.txt
