Metadata-Version: 2.0
Name: sigopt-python
Version: 1.1.1
Summary: SigOpt Python API Client
Home-page: https://sigopt.com/
Author: SigOpt
Author-email: support@sigopt.com
License: UNKNOWN
Platform: UNKNOWN
Classifier: Development Status :: 5 - Production/Stable
Classifier: Intended Audience :: Developers
Classifier: License :: OSI Approved :: MIT License
Classifier: Operating System :: OS Independent
Classifier: Programming Language :: Python
Classifier: Topic :: Software Development :: Libraries :: Python Modules
Requires-Dist: requests (==2.5.1)
Requires-Dist: simplejson (>=3.5.2)
Requires-Dist: six (==1.10.0)
